<?xml version="1.0"?>
<c level="subseries" id="ref5151"> <did> <unittitle> Correspondence - Alphabetical </unittitle> </did> <c id="ref5152"/> <c id="ref5153"/> <c id="ref5154"/> <c id="ref5155"/> <c id="ref5156"/> <c id="ref5157"/> <c id="ref5158"/> <c id="ref5159"/> <c id="ref5160"/> <c id="ref5161"/> <c id="ref5162"/> <c id="ref5163"/> <c id="ref5164"/> <c id="ref5165"/> <c id="ref5166"/> <c id="ref5167"/> <c id="ref5168"/> <c id="ref5169"/> <c id="ref5170"/> <c id="ref5171"/> <c id="ref5172"/> <c id="ref5173"/> <c id="ref5174"/> <c id="ref5175"/> <c id="ref5176"/> <c id="ref5177"/> </c>
