<?xml version="1.0"?>
<c level="subseries" id="ref920"> <did> <unittitle> Legislation - Miscellaneous</unittitle> </did> <c id="ref921"/> <c id="ref922"/> <c id="ref923"/> <c id="ref924"/> <c id="ref925"/> <c id="ref926"/> <c id="ref927"/> <c id="ref928"/> <c id="ref929"/> <c id="ref930"/> <c id="ref931"/> <c id="ref932"/> <c id="ref933"/> <c id="ref934"/> <c id="ref935"/> <c id="ref936"/> <c id="ref937"/> <c id="ref938"/> <c id="ref939"/> <c id="ref940"/> <c id="ref941"/> <c id="ref942"/> <c id="ref943"/> <c id="ref944"/> <c id="ref945"/> <c id="ref946"/> <c id="ref947"/> <c id="ref948"/> <c id="ref949"/> <c id="ref950"/> <c id="ref951"/> <c id="ref952"/> <c id="ref953"/> <c id="ref954"/> <c id="ref955"/> <c id="ref956"/> <c id="ref957"/> <c id="ref958"/> <c id="ref959"/> <c id="ref960"/> <c id="ref961"/> <c id="ref962"/> <c id="ref963"/> <c id="ref964"/> <c id="ref965"/> <c id="ref966"/> <c id="ref967"/> <c id="ref968"/> <c id="ref969"/> <c id="ref970"/> <c id="ref971"/> <c id="ref972"/> <c id="ref973"/> <c id="ref974"/> <c id="ref975"/> <c id="ref976"/> <c id="ref977"/> <c id="ref978"/> <c id="ref979"/> </c>
