<?xml version="1.0"?>
<c id="ref1404" level="subseries"> <did> <unitid type="aspace_uri">/repositories/2/archival_objects/229963</unitid> <unitdate datechar="creation">2000 Nov.-2001 Mar.</unitdate> </did> <c id="ref1405" level="file"/> <c id="ref1406" level="file"/> <c id="ref1407" level="file"/> <c id="ref1408" level="file"/> <c id="ref1409" level="file"/> <c id="ref1410" level="file"/> <c id="ref1411" level="file"/> <c id="ref1412" level="file"/> <c id="ref1413" level="file"/> <c id="ref1414" level="file"/> <c id="ref1415" level="file"/> <c id="ref1416" level="file"/> <c id="ref1417" level="file"/> <c id="ref1418" level="file"/> <c id="ref1419" level="file"/> <c id="ref1420" level="file"/> <c id="ref1421" level="file"/> <c id="ref1422" level="file"/> <c id="ref1423" level="file"/> <c id="ref1424" level="file"/> <c id="ref1425" level="file"/> </c>
