<?xml version="1.0"?>
<c id="ref2773" level="file"> <did> <unittitle>Notre Dame vs. UK (Game Notes)</unittitle> <unitid type="aspace_uri">/repositories/2/archival_objects/936992</unitid> <unitdate datechar="creation" type="inclusive">2002 Jan 19</unitdate> <container id="aspace_bdd941bf77b423ef72c1da3413f7fa68" label="mixed materials" type="box">2008ua025-P-178</container> <container id="aspace_6489173cbd6b9bb678711c705e30729d" parent="aspace_bdd941bf77b423ef72c1da3413f7fa68" type="folder">66</container> </did> </c>
