<?xml version="1.0"?>
<c id="ref208" level="file"> <did> <unittitle>Ismid Court No. 64 Deputies and Clarence Ayers, Advisor</unittitle> <unitid type="aspace_uri">/repositories/2/archival_objects/941447</unitid> <unitdate datechar="creation" type="inclusive">undated</unitdate> <container id="aspace_ee089eea941246d3c280e961e1eb9ab6" label="graphic materials" type="box">13</container> <container id="aspace_6908a1e3d1bd1750cfb850232b5f2c5c" parent="aspace_ee089eea941246d3c280e961e1eb9ab6" type="item">111</container> </did> </c>
