<?xml version="1.0"?>
<c id="ref137" level="file"> <did> <unittitle>Dorcas Chapter No. 29, North Eastern Avenue, Masonic Hall, Lexington, Kentucky photograph</unittitle> <unitid type="aspace_uri">/repositories/2/archival_objects/939925</unitid> <unitdate datechar="creation" type="inclusive">undated</unitdate> <container id="aspace_76b9fd4791239e74c0d92cded1c97502" label="mixed materials" type="box">6</container> <container id="aspace_1061fe475b020bd82b366978dbfc7734" parent="aspace_76b9fd4791239e74c0d92cded1c97502" type="folder">11</container> </did> </c>
