<?xml version="1.0"?>
<c id="ref184" level="item"> <did> <unittitle>Wheelbarrows in upright storage, hand written on back of image - <emph render="doublequote">Wheelbarrows- Greenbelt, Maryland</emph></unittitle> <unitid type="aspace_uri">/repositories/2/archival_objects/776386</unitid> <unitdate datechar="creation" type="inclusive">undated</unitdate> <container id="aspace_f269d3852e3fdd2916e4e251887420b5" label="graphic materials" type="box">21</container> <container id="aspace_2d81dfcffb97a81edcafcb22adf9a8cd" parent="aspace_f269d3852e3fdd2916e4e251887420b5" type="item">16</container> <dao entityref="xt737p8tb81t_107_1"/> </did> <scopecontent id="aspace_89cd0f36e6be85744957685c7960813f"> <head>Scope and Contents</head> <p>Resettlement Administration Photograph by Mydans</p> </scopecontent> </c>
