<?xml version="1.0"?>
<c id="ref1872" level="file"> <did> <unittitle>Correspondence and Documents - (M-Z) - Claims, Deed, Pendennis Club Membership...</unittitle> <unitid type="aspace_uri">/repositories/2/archival_objects/115577</unitid> <unitdate datechar="creation" type="inclusive">1930 March 6-December 31</unitdate> <container id="aspace_66ca6a9310672295a4c4f69805ebf79a" label="mixed materials" type="box">200</container> <container id="aspace_a0e52ab1b3457cba14e7c5662a49bad9" parent="aspace_66ca6a9310672295a4c4f69805ebf79a" type="folder">1</container> </did> </c>
