<?xml version="1.0"?>
<c id="ref2385" level="file"> <did> <unittitle>Louisville Bicentennial Corporation (Folder D)</unittitle> <unitid type="aspace_uri">/repositories/2/archival_objects/116103</unitid> <unitdate datechar="creation" type="inclusive">undated</unitdate> <container id="aspace_27147fe77a61ce2718818630ce37cfcd" label="mixed materials" type="box">256</container> <container id="aspace_6d19e4f0cc47592c406c70930b82089f" parent="aspace_27147fe77a61ce2718818630ce37cfcd" type="folder">9</container> </did> </c>
