<?xml version="1.0"?>
<c id="ref4998" level="item"> <did> <unittitle>1962 Senatorial Campaign Negatives; Wyatt talking to a man sitting on a tractor</unittitle> <unitid type="aspace_uri">/repositories/2/archival_objects/119222</unitid> <unitdate datechar="creation" type="inclusive">undated</unitdate> <physdesc id="aspace_9720d821616f0aa319ae07bc0662c67c" label="General Physical Description note">4 x 5 safety neg.</physdesc> <container id="aspace_bf283adf918024befc57a5c1ab0bdc8a" label="graphic materials" type="box">435</container> <container id="aspace_045be86a86a5cb098b4696ccdfe02cbd" parent="aspace_bf283adf918024befc57a5c1ab0bdc8a" type="item">2197</container> </did> </c>
