<?xml version="1.0"?>
<c id="ref6331" level="item"> <did> <unittitle>Adlai Stevenson (middle) with unidentified man</unittitle> <unitid type="aspace_uri">/repositories/2/archival_objects/120844</unitid> <unitdate datechar="creation" type="inclusive">circa 1956</unitdate> <physdesc id="aspace_7439359e8c33365fff386d5f794e3662" label="General Physical Description note">10 x 8 color photo</physdesc> <container id="aspace_3d383451b802cc3dacdfc9d64b28b292" label="graphic materials" type="box">447</container> <container id="aspace_aabe4cb032509d6c49ce8a904285b14c" parent="aspace_3d383451b802cc3dacdfc9d64b28b292" type="item">3814</container> </did> </c>
