<?xml version="1.0"?>
<c id="ref5" level="file"> <did> <unittitle>Democratic Primary Election Expenditures and Receipts Statements of opponents</unittitle> <unitid type="aspace_uri">/repositories/2/archival_objects/72903</unitid> <unitdate datechar="creation">1912</unitdate> <container id="aspace_beb41c6eaec87afbf339310d9b517597" label="mixed materials" type="box">1</container> <container id="aspace_06e250f36acfdc508b513f9948eb0720" parent="aspace_beb41c6eaec87afbf339310d9b517597" type="folder">4</container> </did> </c>
