<?xml version="1.0"?>
<c id="ref2248" level="file"> <did> <unittitle>Miscellaneous - Roads - Federal Responsibility for Our Highways from the American Association of State Highway Officials (1925); The AAA Motorists' Program for Better Highways from the American Automobile Association (ca. 1956); Various materials from the Eastern Highway Transport Conference (1953); Agendas and regulations from two Pan American Highway Congresses (1951, 1952); Message to the New Jersey Legislature from Gov. George S. Silzer (1923); Program from a national conference on highway financing sponsored by the U.S. Chamber of Commerce (1955)</unittitle> <unitid type="aspace_uri">/repositories/2/archival_objects/75136</unitid> <container id="aspace_0819f76f889b4e317ac2cfaf0d55374f" label="mixed materials" type="box">191</container> <container id="aspace_150448e0157a46897d2848b269e469ac" parent="aspace_0819f76f889b4e317ac2cfaf0d55374f" type="folder">6</container> </did> </c>
