<?xml version="1.0"?>
<c id="ref1118" level="file"> <did> <unittitle>Miscellaneous - M - April to July - Moroccan Office of Information and Documentation, Istiqlal Party of Morocco, "American Public Opinion on Morocco", 8 Pages</unittitle> <unitid type="aspace_uri">/repositories/2/archival_objects/74008</unitid> <unitdate datechar="creation">1955</unitdate> <container id="aspace_7279785ea68692650c1984151998d8da" label="mixed materials" type="box">109</container> <container id="aspace_7d48faff4c80d88529d217e9d3ca9dcf" parent="aspace_7279785ea68692650c1984151998d8da" type="folder">2</container> </did> </c>
