<?xml version="1.0"?>
<c id="ref21" level="file"> <did> <unittitle><emph render="doublequote">A Dozen Women - Alone and With Men</emph>, selected woodcuts and drawings by Fritz Kredel (2 copies)</unittitle> <unitid type="aspace_uri">/repositories/2/archival_objects/928058</unitid> <unitdate datechar="creation" type="inclusive">2013</unitdate> <container id="aspace_ecd83a1fd2f8717e7c6dd12867075947" label="mixed materials" type="box">3</container> <container id="aspace_03c1c9f1b9b35f3f10debf7da1cd4977" parent="aspace_ecd83a1fd2f8717e7c6dd12867075947" type="folder">60</container> </did> </c>
