<?xml version="1.0"?>
<c id="ref302" level="file"> <did> <unittitle>Matthew Harris Jouett Paintings Catalogue</unittitle> <unitid type="aspace_uri">/repositories/2/archival_objects/179585</unitid> <unitdate datechar="creation">1939</unitdate> <container id="aspace_97f3ad4935d3363351b29af9ed912eab" label="mixed materials" type="box">35</container> <container id="aspace_560c3ebcbf929e74db8b2dca261674bd" parent="aspace_97f3ad4935d3363351b29af9ed912eab" type="folder">4</container> </did> <scopecontent id="aspace_480858b9fa020b47f395fa6235c746bb"> <head>Scope and Contents</head> <p>This folder contains a catalogue of paintings by Matthew Harris Jouett written by Mrs. William H. Martin of Lexington, Kentucky, and published by the J.B. Speed Memorial Museum in Louisville, Kentucky, in 1939.</p> </scopecontent> </c>
