<?xml version="1.0"?>
<c id="ref4145" level="file"> <did> <unittitle>General Soil and Slope Interpretation Guide/ North Georgia Planning and Development Commission; March 1974. GA-04-06-1022</unittitle> <unitid type="aspace_uri">/repositories/2/archival_objects/294106</unitid> <container id="aspace_5fb601a1efcb39d7078631087aaa871f" label="mixed materials" type="box">530</container> <container id="aspace_ad7c79f56ce9203c597de1b43b565646" parent="aspace_5fb601a1efcb39d7078631087aaa871f" type="folder">3</container> </did> </c>
