<?xml version="1.0"?>
<c id="ref2232" level="item"> <did> <unittitle>Governor Combs meeting with staff in West Liberty</unittitle> <unitid type="aspace_uri">/repositories/2/archival_objects/978841</unitid> <unitdate datechar="creation" type="inclusive">1962 August 14</unitdate> <container id="aspace_9d1feef0c113686facd5cf5b8fc8f79c" label="graphic materials" type="box">130</container> <container id="aspace_052d6c65dfacef62e5804fb271716042" parent="aspace_9d1feef0c113686facd5cf5b8fc8f79c" type="item">31</container> </did> </c>
