<?xml version="1.0"?>
<c id="ref1484" level="file"> <did> <unittitle>Subject - Speeches By Other People - President John F. Kennedy</unittitle> <unitid type="aspace_uri">/repositories/2/archival_objects/122387</unitid> <unitdate datechar="creation" type="inclusive">undated</unitdate> <container id="aspace_5cb48e057ae3deb086dc27c6c8cbf363" label="mixed materials" type="box">85</container> <container id="aspace_76279de54a8867c08486bb891a4a31b8" parent="aspace_5cb48e057ae3deb086dc27c6c8cbf363" type="folder">11</container> </did> </c>
