<?xml version="1.0"?>
<c id="ref922" level="file"> <did> <unittitle>Statement Regarding Veterans' Bonus Sales and Use Tax Bill</unittitle> <unitid type="aspace_uri">/repositories/2/archival_objects/121824</unitid> <unitdate datechar="creation" type="inclusive">1960 January 20</unitdate> <container id="aspace_473426cd10dc2973e4697cf46b15c435" label="mixed materials" type="box">67</container> <container id="aspace_333ae4d8e2a72f3e7120d01780c3069f" parent="aspace_473426cd10dc2973e4697cf46b15c435" type="folder">15</container> </did> </c>
