<?xml version="1.0"?>
<c id="ref26" level="file"> <did> <unittitle>Personal accounts, volume 36</unittitle> <unitid type="aspace_uri">/repositories/2/archival_objects/48613</unitid> <unitdate datechar="creation" type="inclusive">1899 August 25-1902 March 13</unitdate> <container id="aspace_b7ecea6ccd802d73ec5b8aa8fe6aae84" label="mixed materials" type="box">6</container> <container id="aspace_880a1d9a348b023cbdb503829af2ce0f" parent="aspace_b7ecea6ccd802d73ec5b8aa8fe6aae84" type="folder">1</container> </did> </c>
