<?xml version="1.0"?>
<c id="ref2471" level="collection"> <did> <unittitle>Wrestling (Results/Brackets/Statistics)</unittitle> <unitid type="aspace_uri">/repositories/2/archival_objects/962669</unitid> <unitdate datechar="creation" type="inclusive">1982-1983</unitdate> <container id="aspace_ffb1d112029b9c8370ffbbd378ef06e9" label="mixed materials" type="box">2008ua025-P-183</container> <container id="aspace_691c5e377500c84a9c292b41ea1314aa" parent="aspace_ffb1d112029b9c8370ffbbd378ef06e9" type="folder">18</container> </did> </c>
