<?xml version="1.0"?>
<c id="ref68" level="file"> <did> <unittitle>United States Department of Treasury</unittitle> <unitid type="aspace_uri">/repositories/2/archival_objects/129953</unitid> <unitdate datechar="creation">1887-1888</unitdate> <container id="aspace_063478bb8d77268bc80628224dbde57d" label="mixed materials" type="box">7</container> <container id="aspace_3dedb403e4d24e067d8ec21688294806" parent="aspace_063478bb8d77268bc80628224dbde57d" type="folder">7</container> <dao entityref="xt7ghx15n565_66_1"/> </did> </c>
