<?xml version="1.0"?>
<c id="ref123" level="item"> <did> <unittitle>American College of Trial Lawyers admission plaque</unittitle> <unitid type="aspace_uri">/repositories/2/archival_objects/982159</unitid> <unitdate datechar="creation" type="inclusive">1962 August 5</unitdate> <container id="aspace_9e7b62c006de476152472336f62ef698" label="mixed materials" type="box">8</container> <container id="aspace_03f39d51f2bb6bbc2700f025ec9c857c" parent="aspace_9e7b62c006de476152472336f62ef698" type="item">1</container> </did> </c>
