<?xml version="1.0"?>
<c id="ref314" level="file"> <did> <unittitle>Jim and/or Christine Simpson to Harriette and Harold Arnow</unittitle> <unitid type="aspace_uri">/repositories/2/archival_objects/308763</unitid> <unitdate datechar="creation">1944 April 23-circa 1984, undated</unitdate> <container id="aspace_99270638051cb9c658f75151fca92e0a" label="mixed materials" type="box">26</container> <container id="aspace_290b31b04a9f22884d4fd5d64b903174" parent="aspace_99270638051cb9c658f75151fca92e0a" type="folder">10</container> </did> </c>
