<?xml version="1.0"?>
<c id="ref431" level="file"> <did> <unitid type="aspace_uri">/repositories/2/archival_objects/308880</unitid> <unitdate datechar="creation">1954 January 2-April 11</unitdate> <container id="aspace_fba84e5959c667341840a66e741e88a6" label="mixed materials" type="box">34</container> <container id="aspace_4a65432edbd19b55c3d1c2f82eb82440" parent="aspace_fba84e5959c667341840a66e741e88a6" type="folder">14</container> </did> <scopecontent id="aspace_6ac311d87c458e18312ff45b32b6decc"> <head>Scope and Contents note</head> <p>Correspondence includes: an inquiring letter from HSA to Michigan Senator Charles E. Potter concerning his cooperation with Senator Joseph McCarthy and the Un-American Activities Committee; a letter from HSA's Berea English professor, E.J. Weekes, who had moved to California and <title render="doublequote">lived around the corner</title> from writer Ruth Suckow; an appreciative reply from Arkansas Senator J.W. Fulbright concerning HSA's endorsement of his <title render="doublequote">views about the McCarthy appropriation</title>; from HSA to U.S. Attorney General Herbert Brownell claiming she was <title render="doublequote">amazed and appalled </title>to hear Senator McCarthy declare the American Civil Liberties Union (ACLU) <title render="doublequote">subversive</title>; two drafts of a sharply critical letter (one ten pages and another 17 pages)to the Superintendent of Washtenaw County Schools reviewing problems HSA's children had while enrolled at the rural Hagen elementary; from HSA to Mrs. Viola Hart, seeking name of radio commentator who had remembered <title render="italic">Hunter's Horn</title> so HSA could send a free copy of <title render="italic">The Dollmaker</title>; congratulations on reviews of the new book, <title render="italic">The Dollmaker</title>, from back home (Bernice Mitchell, Margaret Frye, Mary Wait); information from Marcellus Frost about corn, whiskey, and mules; a reply from the Attorney General's office with an attached list of designated (i.e., subversive) organizations, which does not include the ACLU.</p> </scopecontent> </c>
