<?xml version="1.0"?>
<c id="ref163" level="file"> <did> <unittitle> <title render="italic">Last Town &amp; Country</title> </unittitle> <unitid type="aspace_uri">/repositories/2/archival_objects/789143</unitid> <unitdate datechar="creation" type="inclusive">1982 April</unitdate> <container id="aspace_12bb9bd5ea6a64c43b82f3a9bb60978d" label="moving images" type="box">3</container> <container id="aspace_185c07c9b355f857efa20fe2a16c7696" parent="aspace_12bb9bd5ea6a64c43b82f3a9bb60978d" type="item">4</container> </did> </c>
