<?xml version="1.0"?>
<c id="ref7" level="file"> <did> <unittitle>B. Irvin letter to unidentified sister</unittitle> <unitid type="aspace_uri">/repositories/2/archival_objects/948458</unitid> <unitdate datechar="creation" normal="1851/1851" type="inclusive">1851 October 23</unitdate> <container id="aspace_77d61c89db070736e463df9eb91e8f78" label="mixed materials" type="box">1</container> <container id="aspace_7bdae93e5444f92d7e51d320876427c2" parent="aspace_77d61c89db070736e463df9eb91e8f78" type="folder">6</container> </did> </c>
