<?xml version="1.0"?>
<c id="ref60" level="file"> <did> <unittitle>John H. Irvin letter to Samuel L. Irvin</unittitle> <unitid type="aspace_uri">/repositories/2/archival_objects/948517</unitid> <unitdate datechar="creation" normal="1831/1831" type="inclusive">1831 August 29</unitdate> <container id="aspace_dc5931f2c5372ef4af665a3503157a13" label="mixed materials" type="box">1</container> <container id="aspace_762b2dabb7f31fc8943039e1e73250e1" parent="aspace_dc5931f2c5372ef4af665a3503157a13" type="folder">59</container> </did> </c>
