<?xml version="1.0"?>
<c id="ref738" level="series"> <did> <unittitle>Artifacts</unittitle> <unitid>Series V.</unitid> <unitdate datechar="creation" type="inclusive">1982-2010, undated</unitdate> </did> <scopecontent id="aspace_216b8e30e39acb71662bc00861762315"> <head>Scope and Contents</head> <p>Comprises festival and performance admission bracelets, buttons, badges, passes, patches, and stickers. Also includes performance buttons and badges for performers Bev Futrell and Karen Jones.</p> </scopecontent> <c id="ref739" level="subseries"/> <c id="ref740" level="subseries"/> <c id="ref744" level="subseries"/> <c id="ref745" level="subseries"/> <c id="ref746" level="subseries"/> <c id="ref750" level="subseries"/> </c>
