<?xml version="1.0"?>
<c id="ref144" level="item"> <did> <unittitle><title render="doublequote">Folk Songs of the Kentucky Mountains</title>, Josephine McGill, Boosey and Company, New York, New York</unittitle> <unitdate datechar="creation" type="inclusive">1917</unitdate> <container id="aspace_d5d68f377809b98c908d4fd60e72bf71" label="mixed materials" type="box">2</container> <container id="aspace_8ec4b0c4be486ca1f98cfca60a53dcb5" parent="aspace_d5d68f377809b98c908d4fd60e72bf71" type="item">62</container> </did> </c>
