<?xml version="1.0"?>
<c id="ref1501" level="file"> <did> <unittitle>Armored School, Fort Knox, Command Conference, Lesson Plan, and Army Discussion Topic 8 handbook</unittitle> <unitdate datechar="creation" type="inclusive">1952</unitdate> <container id="aspace_08f8b3cd96c5769f7015b6a2561fe2c7" label="mixed materials" type="box">2018ms036-08</container> <container id="aspace_4787ead4c230fe37292513f228cb5d52" parent="aspace_08f8b3cd96c5769f7015b6a2561fe2c7" type="folder">48</container> </did> </c>
