<?xml version="1.0"?>
<c id="ref194" level="item"> <did> <unittitle>Portrait of a young woman. <emph render="doublequote">Brooks.</emph></unittitle> <unitid type="aspace_uri">/repositories/2/archival_objects/168413</unitid> <unitdate datechar="creation" type="inclusive">undated</unitdate> <container id="aspace_8e2a66477dbb22ddfdd6df9b0764addc" label="graphic materials" type="box">2</container> <container id="aspace_33a3f2823df659e843c36df8083bdc68" parent="aspace_8e2a66477dbb22ddfdd6df9b0764addc" type="item">173</container> <dao entityref="xt7gqn5z6m6g_174_1"/> </did> <odd id="aspace_869d53d2a13a4d4049f9122686bd41f4"> <head>General note</head> <p>(4x8) b&amp;w print</p> </odd> </c>
