<?xml version="1.0"?>
<c id="ref209" level="file"> <did> <unittitle>Awards and certificates</unittitle> <unitid type="aspace_uri">/repositories/2/archival_objects/946980</unitid> <unitdate datechar="creation" type="inclusive">2005, 2008, 2013, 2016, 2021, undated</unitdate> <container id="aspace_0f8188ad9773039523b4949b853c24c5" label="mixed materials" type="box">2022ms062-06</container> <container id="aspace_0c57c057b08fe492a7c492e98210590a" parent="aspace_0f8188ad9773039523b4949b853c24c5" type="folder">15</container> </did> </c>
