<?xml version="1.0"?>
<c id="ref2070" level="file"> <did> <unittitle><title render="italic">Thoroughbred Record</title> articles: <title render="doublequote">Breaking and Training the Thoroughbred</title> and <title render="doublequote">Breeding Stock and Care of the Young</title></unittitle> <unitdate datechar="creation" type="inclusive">circa 1925</unitdate> <container id="aspace_adf61f7f8f0e6719e8434c999b25c8c2" label="mixed materials" type="box">2018ms036-17</container> <container id="aspace_a5d36da202b60be5ec552c4b249711a2" parent="aspace_adf61f7f8f0e6719e8434c999b25c8c2" type="folder">12</container> </did> </c>
