<?xml version="1.0"?>
<c id="ref1873" level="file"> <did> <unittitle>May Dikeman Hoss, <title render="italic">The Pike</title> [Appleton-Century-Crofts], p. 1-2</unittitle> <unitid type="aspace_uri">/repositories/2/archival_objects/310322</unitid> <unitdate datechar="creation">circa 1954</unitdate> <container id="aspace_93056dc1b711ddbdd4e4a7b070dcc0cc" label="mixed materials" type="box">124</container> <container id="aspace_f1a66856c21ef2d18baa8520e51a6eaf" parent="aspace_93056dc1b711ddbdd4e4a7b070dcc0cc" type="folder">6</container> </did> </c>
