<?xml version="1.0"?>
<c id="ref2401" level="item"> <did> <unittitle>American Federation of Labor banquet honoring Sir Walter Citrine, Willard Hotel, Washington, D.C.</unittitle> <unitdate datechar="creation" type="inclusive">1940 December 10</unitdate> <container id="aspace_ede4203fa2f09480385714d7e0862231" label="graphic materials" type="folder">OS 1</container> <container id="aspace_565d3b4ed8fcaa6cf73660342108981a" parent="aspace_ede4203fa2f09480385714d7e0862231" type="item">770</container> </did> </c>
