<?xml version="1.0"?>
<c id="ref3620" level="item"> <did> <unittitle>Wilson W. Wyatt, Mayoral Campaign speech</unittitle> <unitid type="aspace_uri">/repositories/2/archival_objects/117384</unitid> <unitdate datechar="creation" type="inclusive">1941</unitdate> <physdesc id="aspace_d0446adb22a27d8e625c9294fd170c84" label="General Physical Description note">8 x 10 black and white photo</physdesc> <container id="aspace_cf3ef5d8dd9a748fa95d9e248585338f" label="graphic materials" type="box">411</container> <container id="aspace_ad0e2bbaf2e21c123207488e37046f99" parent="aspace_cf3ef5d8dd9a748fa95d9e248585338f" type="item">264</container> </did> </c>
