<?xml version="1.0"?>
<c id="ref1153" level="file"> <did> <unittitle>County Files - Christian County - Correspondence, Clippings, Memoranda, Speeches, Hopkinsville</unittitle> <unitid type="aspace_uri">/repositories/2/archival_objects/114849</unitid> <unitdate datechar="creation" type="inclusive">undated</unitdate> <container id="aspace_253552d52b733623c3752fddf20c39a4" label="mixed materials" type="box">123</container> <container id="aspace_2adb8d745e7144a2d90341dfd36853fe" parent="aspace_253552d52b733623c3752fddf20c39a4" type="folder">5</container> </did> </c>
