<?xml version="1.0"?>
<c id="ref2718" level="file"> <did> <unittitle>Shakertown - Round-table - <title render="doublequote">Kentucky's 1891 Constitution: The Case for Change in 1991</title></unittitle> <unitid type="aspace_uri">/repositories/2/archival_objects/116443</unitid> <unitdate datechar="creation" type="inclusive">1990 November</unitdate> <container id="aspace_74a0bac22f0a6b400ad52460176e6357" label="mixed materials" type="box">299</container> <container id="aspace_56fdd22e216eba091a2d60badfbbf358" parent="aspace_74a0bac22f0a6b400ad52460176e6357" type="folder">9-10</container> </did> </c>
