<?xml version="1.0"?>
<c id="ref4632" level="item"> <did> <unittitle>Wilson Wyatt, Steve Murphy, Morton Holbrook and Murphy Miller in Owensboro Fire Dept. automobile; Industrial Appreciation Day. Owensboro</unittitle> <unitid type="aspace_uri">/repositories/2/archival_objects/118728</unitid> <unitdate datechar="creation" type="inclusive">1961 June 14</unitdate> <physdesc id="aspace_cb847d2550d207786d7890323c53b832" label="General Physical Description note">8 x 10 black and white photo</physdesc> <container id="aspace_cb06e27be6f672e1dd8dbdade8fdda63" label="graphic materials" type="box">429</container> <container id="aspace_c274cff70924f3a21b0973fd32d3e598" parent="aspace_cb06e27be6f672e1dd8dbdade8fdda63" type="item">1604</container> </did> </c>
