<?xml version="1.0"?>
<c id="ref2599" level="file"> <did> <unittitle>Regional Cancer Center Corp - Board of Directors - Minutes</unittitle> <unitid type="aspace_uri">/repositories/2/archival_objects/116319</unitid> <unitdate datechar="creation" type="inclusive">1981 December-1982 May</unitdate> <container id="aspace_7f4bf7c4e125d3a291bd63a7e4c7335c" label="mixed materials" type="box">284</container> <container id="aspace_857b4fc7149a0e805e7d62559ad58bb1" parent="aspace_7f4bf7c4e125d3a291bd63a7e4c7335c" type="folder">2</container> </did> </c>
