<?xml version="1.0"?>
<c id="ref1882" level="file"> <did> <unittitle>Correspondence and Documents - (L-P) - Claims, Last Will and Testament, Louisville Bar ....</unittitle> <unitid type="aspace_uri">/repositories/2/archival_objects/115588</unitid> <unitdate datechar="creation" type="inclusive">1933</unitdate> <container id="aspace_4e7a7303d2d660e7273442fdc4782472" label="mixed materials" type="box">201</container> <container id="aspace_f90c7c8a21d3f2eda7f76578fa24554e" parent="aspace_4e7a7303d2d660e7273442fdc4782472" type="folder">6</container> </did> </c>
