<?xml version="1.0"?>
<c id="ref309" level="file"> <did> <unittitle>Religious Tracts</unittitle> <unitid type="aspace_uri">/repositories/2/archival_objects/179592</unitid> <unitdate datechar="creation">1901-1917, 1940, undated</unitdate> <container id="aspace_ac1c3cfc570a1f92c0d369c274fb1258" label="mixed materials" type="box">35</container> <container id="aspace_0c58bd7bf5705509a0af4ac3c3c796a8" parent="aspace_ac1c3cfc570a1f92c0d369c274fb1258" type="folder">11</container> </did> <scopecontent id="aspace_b60b3c25dd7c726d73cf6eee9027aa72"> <head>Scope and Contents</head> <p>This folder contains several Christian pamphlets and booklets, a book of Catholic hymns, a bound Christian text, and a 1940 calendar asking for donations to the Christian-run hospital for Hansen's disease (leprosy) in Kumamoto, Japan.</p> </scopecontent> </c>
