<?xml version="1.0"?>
<c id="ref1052" level="subseries"> <did> <unitid type="aspace_uri">/repositories/2/archival_objects/229891</unitid> <unitdate datechar="creation">1989 Oct.-1990 Apr.</unitdate> </did> <c id="ref1053" level="file"/> <c id="ref1054" level="file"/> <c id="ref1055" level="file"/> <c id="ref1056" level="file"/> <c id="ref1057" level="file"/> <c id="ref1058" level="file"/> <c id="ref1059" level="file"/> <c id="ref1060" level="file"/> <c id="ref1061" level="file"/> <c id="ref1062" level="file"/> <c id="ref1063" level="file"/> <c id="ref1064" level="file"/> <c id="ref1065" level="file"/> <c id="ref1066" level="file"/> <c id="ref1067" level="file"/> <c id="ref1068" level="file"/> <c id="ref1069" level="file"/> <c id="ref1070" level="file"/> <c id="ref1071" level="file"/> <c id="ref1072" level="file"/> <c id="ref1073" level="file"/> <c id="ref1074" level="file"/> <c id="ref1075" level="file"/> <c id="ref1076" level="file"/> </c>
