<?xml version="1.0"?>
<c id="ref1188" level="file"> <did> <unittitle>UK vs. Robert Morris (SWISH Magazine)</unittitle> <unitid type="aspace_uri">/repositories/2/archival_objects/684282</unitid> <unitdate datechar="creation" type="inclusive">1993 Dec. 30</unitdate> <container id="aspace_43d3ccb8ebd4a3165e9d5309a7c3ee83" label="mixed materials" type="box">2008ua025-P-150</container> <container id="aspace_799c1f7ac310022a8be62b0ffdf15992" parent="aspace_43d3ccb8ebd4a3165e9d5309a7c3ee83" type="folder">10</container> </did> </c>
