<?xml version="1.0"?>
<c id="ref104" level="series"> <did> <unittitle>Prince Hall Grand Lodge</unittitle> <unitid>Series II.</unitid> <unitdate datechar="creation" type="inclusive">1968-2002, undated</unitdate> </did> <scopecontent id="aspace_f54dc8bc222e9afae6e4f666a79a6c00"> <head>Scope and Contents</head> <p>This series contains documents concerning the Prince Hall Grand Lodge and its members. It holds various official business papers such as articles of incorporation and amendment as well as correspondence and documents detailing membership benefits. Also included are annual communications from the Lodge.</p> </scopecontent> <c id="ref105" level="subseries"/> <c id="ref115" level="subseries"/> <c id="ref120" level="subseries"/> <c id="ref124" level="subseries"/> <c id="ref129" level="subseries"/> </c>
