<?xml version="1.0"?>
<c id="ref191" level="file"> <did> <unittitle>Agriculture, Rural Development, and the Use of Land, A Series of Papers Compiled by the Subcommittee of the Committee on Agriculture and Forestry. April 16, 1974</unittitle> <unitid type="aspace_uri">/repositories/2/archival_objects/290152</unitid> <container id="aspace_384ecf4731021e24cca0d5aa2ef8ef2e" label="mixed materials" type="box">13</container> <container id="aspace_ed3ce3d40f68b78faf4e107669c07b26" parent="aspace_384ecf4731021e24cca0d5aa2ef8ef2e" type="folder">4</container> </did> </c>
