<?xml version="1.0"?>
<c id="ref5770" level="file"> <did> <unittitle>Survey of Auxiliary Health and Education Personnel in Nine Counties of Southern West Virginia/Training Corporation of America, Inc.; September 1968</unittitle> <unitid type="aspace_uri">/repositories/2/archival_objects/295731</unitid> <container id="aspace_1f9020b1af26a7de21ad33a615ec2e6c" label="mixed materials" type="box">516</container> <container id="aspace_98de01637d0e6a267ffef03a27a2df9c" parent="aspace_1f9020b1af26a7de21ad33a615ec2e6c" type="folder">5</container> </did> </c>
