<?xml version="1.0"?>
<c id="ref5966" level="file"> <did> <unittitle>The Impact of Mine Drainage Pollution on Industrial Water Users in Appalachia: Appendix A to <emph render="underline">Acid Mine Drainage in Appalachia</emph>/ Battelle Memorial Institute; March 1969</unittitle> <unitid type="aspace_uri">/repositories/2/archival_objects/295927</unitid> <container id="aspace_6071a3136ba3ffa77c1c631afbd95cbf" label="mixed materials" type="box">552</container> <container id="aspace_99b2998671fa1fa5bc324c8e0df74651" parent="aspace_6071a3136ba3ffa77c1c631afbd95cbf" type="folder">4</container> </did> </c>
