<?xml version="1.0"?>
<c id="ref4349" level="file"> <did> <unittitle>Surface Mine Pollution Abatement and Land Use Impact Investigation, Vol. 4: An Investigation of the Alternative Data Systems with a Recommendation for a Statewide Environmental Storage and Retrieval system/ Eastern Kentucky University; August 1975</unittitle> <unitid type="aspace_uri">/repositories/2/archival_objects/294310</unitid> <container id="aspace_455b39074d7eb2f960742985218c6eba" label="mixed materials" type="box">396</container> <container id="aspace_b719dcd2f057ba778d080e02f37c9aab" parent="aspace_455b39074d7eb2f960742985218c6eba" type="folder">4</container> </did> </c>
