<?xml version="1.0"?>
<c id="ref8464" level="file"> <did> <unittitle>Estimate of the Cost of Improving Inadequate Segments of the Appalachian Development Highway System in the State of West Virginia/ State Road Commission of West Virginia; March 1966</unittitle> <unitid type="aspace_uri">/repositories/2/archival_objects/298425</unitid> <container id="aspace_c7801325c6b44495a79a005c04046dfd" label="mixed materials" type="box">538</container> <container id="aspace_22cc0f650dc14974f262b7010d793f8c" parent="aspace_c7801325c6b44495a79a005c04046dfd" type="folder">1</container> </did> </c>
