<?xml version="1.0"?>
<c id="ref7" level="item"> <did> <unittitle>Gothic Chapel; large cave interior with large stalactites</unittitle> <unitid type="aspace_uri">/repositories/2/archival_objects/947400</unitid> <unitdate datechar="creation" type="inclusive">1866</unitdate> <container id="aspace_25086d1a0c26d94d9d717335822cc372" label="graphic materials" type="box">1</container> <container id="aspace_d4c8295b01c2c0bbe27268b539c4684e" parent="aspace_25086d1a0c26d94d9d717335822cc372" type="image">7</container> </did> </c>
