<?xml version="1.0"?>
<c id="ref492" level="file"> <did> <unittitle> <title render="italic">Louisville Courier Journal </title> </unittitle> <unitid type="aspace_uri">/repositories/2/archival_objects/391935</unitid> <unitdate datechar="creation">1980 March 2</unitdate> <container id="aspace_2228cc6fd69ebdb69736a6ec2dd5fd8f" label="mixed materials" type="box">82m9-018</container> <container id="aspace_68cd3256ef369bf8c98a7adb1e11236f" parent="aspace_2228cc6fd69ebdb69736a6ec2dd5fd8f" type="folder">15</container> </did> </c>
