<?xml version="1.0"?>
<c id="ref215" level="file"> <did> <unittitle>Resignation as U.S. Senate Majority Leader - Correspondence; Opposed B (folder 2)</unittitle> <unitid type="aspace_uri">/repositories/2/archival_objects/73113</unitid> <unitdate datechar="creation">1944</unitdate> <container id="aspace_b0364280aa6e91f0273e9f8433020cda" label="mixed materials" type="box">23</container> <container id="aspace_5045ed3dbcc314e7a8f287f0a0b6346c" parent="aspace_b0364280aa6e91f0273e9f8433020cda" type="folder">6</container> </did> </c>
