<?xml version="1.0"?>
<c id="ref272" level="file"> <did> <unittitle>Election, Vice-President - Congratulatory Correspondence H (folder 2)</unittitle> <unitid type="aspace_uri">/repositories/2/archival_objects/73170</unitid> <unitdate datechar="creation">1948</unitdate> <container id="aspace_9acabf209f7c31208b75e8a4d395170d" label="mixed materials" type="box">30</container> <container id="aspace_6733dd7669ac6a3d2e1c10bb63e6751c" parent="aspace_9acabf209f7c31208b75e8a4d395170d" type="folder">1</container> </did> </c>
