<?xml version="1.0"?>
<c id="ref1587" level="file"> <did> <unittitle>Jewish National Fund; Hotel Statler, St. Louis, MO; November 10, 1940.</unittitle> <unitid type="aspace_uri">/repositories/2/archival_objects/74478</unitid> <unitdate datechar="creation">November 10, 1940.</unitdate> <container id="aspace_8c1d05612904af14312548a2d2e7ec28" label="mixed materials" type="box">153</container> <container id="aspace_117e751f90adbe24f0ff276426cc3bae" parent="aspace_8c1d05612904af14312548a2d2e7ec28" type="folder">30</container> </did> </c>
