<?xml version="1.0"?>
<c id="ref2241" level="file"> <did> <unittitle>Miscellaneous - Prohibition - The Progress of Prohibition Enforcement, an address by Federal Prohibition Commissioner R.A. Haynes (1925); Law Observance, an address by Attorney General John G. Sargent (1926); Two booklets from the U.S. Treasury Department Bureau of Prohibition (1930): Padlock Procedure: The Judicial Method of Closing Property Used to Violate the Prohibition Laws and Public Cooperation in Prohibition Law Enforcement</unittitle> <unitid type="aspace_uri">/repositories/2/archival_objects/75129</unitid> <container id="aspace_d4c2cbf0a5f2f4aafb2d91a12deadc03" label="mixed materials" type="box">190</container> <container id="aspace_16967cdc3ac960caeede33f0b3ef3378" parent="aspace_d4c2cbf0a5f2f4aafb2d91a12deadc03" type="folder">16</container> </did> </c>
