<?xml version="1.0"?>
<c id="ref1567" level="file"> <did> <unittitle>"The Democracy of the Soul;" B'nai B'rith Banquet; Pittsburg, PA; May 28, 1939.</unittitle> <unitid type="aspace_uri">/repositories/2/archival_objects/74458</unitid> <unitdate datechar="creation">May 28, 1939.</unitdate> <container id="aspace_5910471d9f4d50d67349ac6acdcff4ab" label="mixed materials" type="box">153</container> <container id="aspace_e52eca08fdcd83ec4436cdee4371e64f" parent="aspace_5910471d9f4d50d67349ac6acdcff4ab" type="folder">10</container> </did> </c>
