<?xml version="1.0"?>
<c id="ref1731" level="file"> <did> <unittitle>Democratic State Convention; Campaign; Municipal Auditorium, Worcester, MA; September 25, 1948.</unittitle> <unitid type="aspace_uri">/repositories/2/archival_objects/74622</unitid> <unitdate datechar="creation">September 25, 1948.</unitdate> <container id="aspace_be3fe175cb6724646943b7c8d8b0b79b" label="mixed materials" type="box">157</container> <container id="aspace_118366315c17d9c71c17312ca106bd55" parent="aspace_be3fe175cb6724646943b7c8d8b0b79b" type="folder">31</container> </did> </c>
