<?xml version="1.0"?>
<c id="ref2271" level="file"> <did> <unittitle>Volleyball: Kentucky vs. Alabama (Final Book)</unittitle> <unitid type="aspace_uri">/repositories/2/archival_objects/563890</unitid> <unitdate datechar="creation" type="inclusive">2006 Nov. 5</unitdate> <container id="aspace_5c5896f7617656abc97926c76e554884" label="mixed materials" type="box">P-112</container> <container id="aspace_4571e47b1e1f6afa0534ea95a2c24670" parent="aspace_5c5896f7617656abc97926c76e554884" type="folder">1</container> </did> </c>
