<?xml version="1.0"?>
<c id="ref2157" level="file"> <did> <unittitle>Kentucky vs. Illinois State (VB Box Scores)</unittitle> <unitid type="aspace_uri">/repositories/2/archival_objects/697013</unitid> <unitdate datechar="creation" type="inclusive">2000 Sept. 9</unitdate> <container id="aspace_289d316765a024989078b119c96abe59" label="mixed materials" type="box">P-112</container> <container id="aspace_218940f75728c34aff3824051e971399" parent="aspace_289d316765a024989078b119c96abe59" type="folder">26</container> </did> </c>
