<?xml version="1.0"?>
<c id="ref2451" level="item"> <did> <unittitle>Rep. Louis T. Peniston (D) New Castle, KY Dist. 57</unittitle> <unitid type="aspace_uri">/repositories/2/archival_objects/980391</unitid> <unitdate datechar="creation" type="inclusive">[1959-1963]</unitdate> <container id="aspace_fb33a31c4de3b95db7268c12f89ef81d" label="graphic materials" type="box">133</container> <container id="aspace_4ccdaea1bb03fb120a767764f88f0948" parent="aspace_fb33a31c4de3b95db7268c12f89ef81d" type="item">8</container> </did> </c>
