<?xml version="1.0"?>
<c id="ref41" level="file"> <did> <unittitle>83-01 Wallace v. Heckler to 83-13 Jackson Purchase Electric Corporation v. International Brotherhood of Electrical Workers, Local Union No. 816</unittitle> <unitid>File</unitid> <unitid type="aspace_uri">/repositories/2/archival_objects/1004941</unitid> <unitdate datechar="creation" type="inclusive">1983-1985</unitdate> <container id="aspace_93171b21a9f2f6c5eac6781dee5b9a7c" label="mixed materails" type="box">4</container> <container id="aspace_f5b03315419cfbd2bed0537f2aba2876" parent="aspace_93171b21a9f2f6c5eac6781dee5b9a7c" type="folder">7-8</container> </did> </c>
