<?xml version="1.0"?>
<c id="ref341" level="file"> <did> <unittitle>Randam Colony, Larasaul, Patanix Lalper, Bhoods India [contact sheets and negatives]</unittitle> <unitid type="aspace_uri">/repositories/2/archival_objects/896043</unitid> <unitdate datechar="creation" type="inclusive">1999-2000</unitdate> <container id="aspace_593b220d7e82043c4a435891e5aaabc3" label="graphic materials" type="box">21</container> <container id="aspace_b9585a69a49902bdf6738790e607e391" parent="aspace_593b220d7e82043c4a435891e5aaabc3" type="folder">9</container> </did> </c>
