<?xml version="1.0"?>
<c id="ref185" level="item"> <did> <unittitle>Crowd gathered for auction of Brezing furniture and personal memorabilia</unittitle> <unitid type="aspace_uri">/repositories/2/archival_objects/156012</unitid> <unitdate datechar="creation">1940</unitdate> <physdesc id="aspace_df5b07910d514a730d4bc8c8ffb985bf" label="General Physical Description note">5 x 7, black and white silver print</physdesc> <container id="aspace_21bac547bb914490a53121d11375cddc" label="mixed materials" type="box">2</container> <container id="aspace_9cf77d93d2353ddbada875e523fd9cd9" parent="aspace_21bac547bb914490a53121d11375cddc" type="item">166</container> <dao entityref="xt7jws8hfb5d_166_1"/> </did> </c>
